helios/__init__.py
helios/__main__.py
helios/bootstrap.py
helios/main.py
helios/core/__init__.py
helios/core/crawler.py
helios/core/database.py
helios/core/engine.py
helios/core/login.py
helios/core/modules.py
helios/core/postback_crawler.py
helios/core/request.py
helios/core/response.py
helios/core/scanner.py
helios/core/scope.py
helios/core/scripts.py
helios/core/utils.py
helios/core/webapps.py
helios/drivers/chromedriver.exe
helios/ext/__init__.py
helios/ext/libcms/__init__.py
helios/ext/libcms/cms_scanner_core.py
helios/ext/libcms/detector.py
helios/ext/libcms/scanners/__init__.py
helios/ext/libcms/scanners/cms_scanner.py
helios/ext/libcms/scanners/drupal.py
helios/ext/libcms/scanners/joomla.py
helios/ext/libcms/scanners/wordpress.py
helios/ext/mefjus/__init__.py
helios/ext/mefjus/ghost.py
helios/ext/mefjus/proxy.py
helios/ext/metamonster/__init__.py
helios/ext/metamonster/detector.py
helios/ext/metamonster/meta_executor.py
helios/ext/metamonster/metamonster.py
helios/ext/metamonster/rpcclient.py
helios/modules/__init__.py
helios/modules/module_backup_files.py
helios/modules/module_base.py
helios/modules/module_robots.py
helios/modules/module_shellshock.py
helios/modules/module_sitemap.py
helios/modules/module_sqli_booleanbased.py
helios/modules/module_sqli_timebased.py
helios/modules/module_stored_xss.py
helios/modules/module_uploads.py
helios/scripts/admin_directory_discovery.json
helios/scripts/admin_portal.json
helios/scripts/attrib_xss.json
helios/scripts/cgi-bin.json
helios/scripts/command_injection.json
helios/scripts/composer.json
helios/scripts/file_inclusion.json
helios/scripts/file_inclusion_abs.json
helios/scripts/file_inclusion_nullbyte.json
helios/scripts/git_repo.json
helios/scripts/header_injection.json
helios/scripts/htaccess.json
helios/scripts/htpasswd.json
helios/scripts/php_application_error.json
helios/scripts/remote_file_inclusion.json
helios/scripts/server_header_exposure.json
helios/scripts/server_powered_by_discovery.json
Helios_Scanner-1.1.dist-info/LICENSE
Helios_Scanner-1.1.dist-info/METADATA
Helios_Scanner-1.1.dist-info/WHEEL
Helios_Scanner-1.1.dist-info/entry_points.txt
Helios_Scanner-1.1.dist-info/top_level.txt
Helios_Scanner-1.1.dist-info/RECORD
