Metadata-Version: 2.1
Name: Helios-Scanner
Version: 1.1
Summary: A Python based Web Application security scanner
Home-page: https://github.com/stefan2200/Helios
Author: stefan2200
Author-email: stefan@stefanvlems.nl
License: Apache 2.0
Platform: UNKNOWN
Classifier: Intended Audience :: Developers
Classifier: Intended Audience :: Information Technology
Classifier: Intended Audience :: System Administrators
Classifier: Development Status :: 4 - Beta
Classifier: Environment :: Console
Classifier: Operating System :: POSIX
Classifier: Operating System :: Microsoft :: Windows
Classifier: Operating System :: MacOS :: MacOS X
Classifier: License :: OSI Approved :: Apache Software License
Classifier: Programming Language :: Python
Classifier: Programming Language :: Python :: 3.5
Classifier: Programming Language :: Python :: 3.6
Classifier: Programming Language :: Python :: 3.7
Classifier: Programming Language :: Python :: 3.8
Classifier: Programming Language :: Python :: 3.9
Classifier: Topic :: Security
Classifier: Topic :: Software Development :: Testing
Classifier: Topic :: Internet :: WWW/HTTP
Classifier: Topic :: Software Development :: Libraries :: Python Modules
Requires-Dist: pyOpenSSL (>=0.14beautifulsoup4)
Requires-Dist: requests
Requires-Dist: selenium
Requires-Dist: filelock
Requires-Dist: msgpack
Requires-Dist: futures ; python_version == "2.7"
